Workbook

Sheet US_Yields
A1: Source: U.S. Department of the Treasury — Daily Treasury Par Yield Curve Rates
A3: Date | B3: 1 Mo | C3: 1.5 Month | D3: 2 Mo | E3: 3 Mo | F3: 4 Mo | G3: 6 Mo | H3: 1 Yr | I3: 2 Yr | J3: 3 Yr | K3: 5 Yr | L3: 7 Yr | M3: 10 Yr | N3: 20 Yr | O3: 30 Yr
A4: 46024 | B4: 3.72 | C4: 3.71 | D4: 3.66 | E4: 3.65 | F4: 3.62 | G4: 3.58 | H4: 3.47 | I4: 3.47 | J4: 3.55 | K4: 3.74 | L4: 3.95 | M4: 4.19 | N4: 4.81 | O4: 4.86
A5: 46027 | B5: 3.71 | C5: 3.68 | D5: 3.64 | E5: 3.64 | F5: 3.61 | G5: 3.57 | H5: 3.47 | I5: 3.46 | J5: 3.53 | K5: 3.71 | L5: 3.92 | M5: 4.17 | N5: 4.79 | O5: 4.85
A6: 46028 | B6: 3.7 | C6: 3.7 | D6: 3.61 | E6: 3.63 | F6: 3.58 | G6: 3.56 | H6: 3.48 | I6: 3.47 | J6: 3.54 | K6: 3.72 | L6: 3.93 | M6: 4.18 | N6: 4.8 | O6: 4.86
A7: 46029 | B7: 3.7 | C7: 3.69 | D7: 3.6 | E7: 3.62 | F7: 3.6 | G7: 3.56 | H7: 3.48 | I7: 3.47 | J7: 3.53 | K7: 3.7 | L7: 3.91 | M7: 4.15 | N7: 4.76 | O7: 4.82
A8: 46030 | B8: 3.7 | C8: 3.69 | D8: 3.63 | E8: 3.62 | F8: 3.6 | G8: 3.56 | H8: 3.48 | I8: 3.49 | J8: 3.56 | K8: 3.74 | L8: 3.95 | M8: 4.19 | N8: 4.79 | O8: 4.85
A9: 46031 | B9: 3.7 | C9: 3.68 | D9: 3.63 | E9: 3.62 | F9: 3.62 | G9: 3.57 | H9: 3.52 | I9: 3.54 | J9: 3.59 | K9: 3.75 | L9: 3.95 | M9: 4.18 | N9: 4.76 | O9: 4.82
A10: 46034 | B10: 3.71 | C10: 3.68 | D10: 3.64 | E10: 3.67 | F10: 3.63 | G10: 3.58 | H10: 3.53 | I10: 3.54 | J10: 3.59 | K10: 3.77 | L10: 3.97 | M10: 4.19 | N10: 4.78 | O10: 4.83
A11: 46035 | B11: 3.72 | C11: 3.72 | D11: 3.66 | E11: 3.67 | F11: 3.63 | G11: 3.59 | H11: 3.51 | I11: 3.53 | J11: 3.57 | K11: 3.75 | L11: 3.95 | M11: 4.18 | N11: 4.77 | O11: 4.83
A12: 46036 | B12: 3.72 | C12: 3.71 | D12: 3.66 | E12: 3.67 | F12: 3.65 | G12: 3.58 | H12: 3.5 | I12: 3.51 | J12: 3.56 | K12: 3.72 | L12: 3.92 | M12: 4.15 | N12: 4.73 | O12: 4.79
A13: 46037 | B13: 3.75 | C13: 3.73 | D13: 3.69 | E13: 3.68 | F13: 3.66 | G13: 3.6 | H13: 3.54 | I13: 3.56 | J13: 3.62 | K13: 3.77 | L13: 3.96 | M13: 4.17 | N13: 4.74 | O13: 4.79
A14: 46038 | B14: 3.75 | C14: 3.72 | D14: 3.68 | E14: 3.67 | F14: 3.66 | G14: 3.6 | H14: 3.55 | I14: 3.59 | J14: 3.67 | K14: 3.82 | L14: 4.02 | M14: 4.24 | N14: 4.79 | O14: 4.83
A15: 46042 | B15: 3.75 | C15: 3.71 | D15: 3.69 | E15: 3.7 | F15: 3.65 | G15: 3.61 | H15: 3.53 | I15: 3.6 | J15: 3.68 | K15: 3.86 | L15: 4.08 | M15: 4.3 | N15: 4.87 | O15: 4.91
... A64: 46112 | B64: 3.74 | C64: 3.73 | D64: 3.72 | E64: 3.7 | F64: 3.7 | G64: 3.72 | H64: 3.68 | I64: 3.79 | J64: 3.81 | K64: 3.92 | L64: 4.11 | M64: 4.3 | N64: 4.88 | O64: 4.88

Sheet JP_Yields
A1: Source: Ministry of Finance Japan — JGB Constant Maturity (jgbcme)
A3: Date | B3: 1Y | C3: 2Y | D3: 3Y | E3: 4Y | F3: 5Y | G3: 6Y | H3: 7Y | I3: 8Y | J3: 9Y | K3: 10Y | L3: 15Y | M3: 20Y | N3: 25Y | O3: 30Y | P3: 40Y
A4: 46027 | B4: 0.928 | C4: 1.194 | D4: 1.325 | E4: 1.5 | F4: 1.62 | G4: 1.709 | H4: 1.814 | I4: 1.922 | J4: 2.02 | K4: 2.111 | L4: 2.655 | M4: 3.002 | N4: 3.347 | O4: 3.393 | P4: 3.505
A5: 46028 | B5: 0.919 | C5: 1.185 | D5: 1.32 | E5: 1.498 | F5: 1.615 | G5: 1.709 | H5: 1.815 | I5: 1.929 | J5: 2.03 | K5: 2.123 | L5: 2.677 | M5: 3.029 | N5: 3.374 | O5: 3.42 | P5: 3.544
A6: 46029 | B6: 0.91 | C6: 1.17 | D6: 1.311 | E6: 1.488 | F6: 1.605 | G6: 1.702 | H6: 1.805 | I6: 1.92 | J6: 2.03 | K6: 2.124 | L6: 2.681 | M6: 3.041 | N6: 3.387 | O6: 3.428 | P6: 3.572
A7: 46030 | B7: 0.871 | C7: 1.129 | D7: 1.269 | E7: 1.444 | F7: 1.554 | G7: 1.651 | H7: 1.751 | I7: 1.865 | J7: 1.982 | K7: 2.083 | L7: 2.649 | M7: 3.028 | N7: 3.39 | O7: 3.435 | P7: 3.595
A8: 46031 | B8: 0.893 | C8: 1.151 | D8: 1.292 | E8: 1.466 | F8: 1.58 | G8: 1.671 | H8: 1.769 | I8: 1.884 | J8: 1.998 | K8: 2.096 | L8: 2.65 | M8: 3.013 | N8: 3.363 | O8: 3.399 | P8: 3.55
A9: 46035 | B9: 0.898 | C9: 1.164 | D9: 1.319 | E9: 1.507 | F9: 1.626 | G9: 1.722 | H9: 1.825 | I9: 1.943 | J9: 2.059 | K9: 2.163 | L9: 2.716 | M9: 3.081 | N9: 3.431 | O9: 3.462 | P9: 3.629
A10: 46036 | B10: 0.909 | C10: 1.186 | D10: 1.338 | E10: 1.521 | F10: 1.647 | G10: 1.736 | H10: 1.842 | I10: 1.96 | J10: 2.077 | K10: 2.182 | L10: 2.747 | M10: 3.099 | N10: 3.457 | O10: 3.486 | P10: 3.649
A11: 46037 | B11: 0.915 | C11: 1.19 | D11: 1.336 | E11: 1.513 | F11: 1.636 | G11: 1.718 | H11: 1.823 | I11: 1.944 | J11: 2.059 | K11: 2.164 | L11: 2.728 | M11: 3.078 | N11: 3.43 | O11: 3.454 | P11: 3.616
A12: 46038 | B12: 0.931 | C12: 1.205 | D12: 1.355 | E12: 1.527 | F12: 1.647 | G12: 1.732 | H12: 1.838 | I12: 1.958 | J12: 2.078 | K12: 2.182 | L12: 2.745 | M12: 3.092 | N12: 3.434 | O12: 3.462 | P12: 3.618
A13: 46041 | B13: 0.951 | C13: 1.23 | D13: 1.382 | E13: 1.561 | F13: 1.691 | G13: 1.791 | H13: 1.903 | I13: 2.026 | J13: 2.15 | K13: 2.266 | L13: 2.843 | M13: 3.174 | N13: 3.519 | O13: 3.562 | P13: 3.721
A14: 46042 | B14: 0.943 | C14: 1.22 | D14: 1.381 | E14: 1.568 | F14: 1.703 | G14: 1.816 | H14: 1.935 | I14: 2.066 | J14: 2.208 | K14: 2.33 | L14: 2.982 | M14: 3.325 | N14: 3.691 | O14: 3.765 | P14: 3.901
A15: 46043 | B15: 0.961 | C15: 1.235 | D15: 1.386 | E15: 1.567 | F15: 1.687 | G15: 1.794 | H15: 1.904 | I15: 2.032 | J15: 2.164 | K15: 2.28 | L15: 2.915 | M15: 3.25 | N15: 3.598 | O15: 3.647 | P15: 3.788
... A61: 46112 | B61: 1.102 | C61: 1.375 | D61: 1.503 | E61: 1.677 | F61: 1.804 | G61: 1.913 | H61: 2.019 | I61: 2.139 | J61: 2.257 | K61: 2.366 | L61: 2.927 | M61: 3.284 | N61: 3.589 | O61: 3.64 | P61: 3.713

Sheet FX_USDJPY
A1: Source: FRED DEXJPUS — Japanese Yen to U.S. Dollar spot rate
A3: Date | B3: USD/JPY
A4: 46022 | B4: 156.8
A5: 46024 | B5: 156.72
A6: 46027 | B6: 156.32
A7: 46028 | B7: 156.7
A8: 46029 | B8: 156.73
A9: 46030 | B9: 156.9
A10: 46031 | B10: 158.07
A11: 46034 | B11: 158.15
A12: 46035 | B12: 159.06
A13: 46036 | B13: 158.13
A14: 46037 | B14: 158.5
A15: 46038 | B15: 158.02
... A65: 46112 | B65: 159.08

Sheet WEO_Macro
A1: Source: IMF World Economic Outlook (DataMapper API)
A3: Indicator | B3: Country | C3: 2024 | D3: 2025 | E3: 2026 | F3: 2027 | G3: 2028 | H3: 2029 | I3: 2030 | J3: 2031
A4: Real GDP growth (%) | B4: NGDP_RPCH
B5: USA | C5: 2.8 | D5: 2.1 | E5: 2.3 | F5: 2.1 | G5: 2.1 | H5: 1.9 | I5: 1.8 | J5: 1.8
B6: JPN | C6: -0.2 | D6: 1.2 | E6: 0.7 | F6: 0.6 | G6: 0.6 | H6: 0.6 | I6: 0.6 | J6: 0.6
A8: Inflation, avg CPI (%) | B8: PCPIPCH
B9: USA | C9: 3 | D9: 2.7 | E9: 3.2 | F9: 2.1 | G9: 2.2 | H9: 2.2 | I9: 2.2 | J9: 2.2
B10: JPN | C10: 2.7 | D10: 3.2 | E10: 2.2 | F10: 2.3 | G10: 2 | H10: 2 | I10: 2 | J10: 2
A12: Gen govt gross debt (% GDP) | B12: GGXWDG_NGDP
B13: USA | C13: 122.3 | D13: 123.9 | E13: 125.8 | F13: 128.6 | G13: 132.1 | H13: 135.5 | I13: 138.9 | J13: 142.1
B14: JPN | C14: 214.5 | D14: 206.5 | E14: 204.4 | F14: 200.1 | G14: 197.7 | H14: 195.7 | I14: 193.9 | J14: 192.8
A16: Current account balance (% GDP) | B16: BCA_NGDPD
B17: USA | C17: -4 | D17: -3.6 | E17: -3.7 | F17: -3.6 | G17: -3.6 | H17: -3.6 | I17: -3.6 | J17: -3.6
B18: JPN | C18: 4.5 | D18: 4.8 | E18: 3.8 | F18: 3.9 | G18: 3.9 | H18: 3.9 | I18: 4.1 | J18: 4.1

Sheet Spreads
A1: Daily US − JP yield differential (basis points). Lookup JP by date.
A3: Tenor | B3: Mean (bp) | C3: Stdev (bp) | D3: Q1 close (bp)
A4: 1Y | B4: =AVERAGE(F10:F1000) | C4: =STDEV(F10:F1000) | D4: =LOOKUP(2,1/(F10:F1000<>""),F10:F1000)
A5: 10Y | B5: =AVERAGE(G10:G1000) | C5: =STDEV(G10:G1000) | D5: =LOOKUP(2,1/(G10:G1000<>""),G10:G1000)
A9: Date | B9: US 1Y (%) | C9: US 10Y (%) | D9: JP 1Y (%) | E9: JP 10Y (%) | F9: Spread 1Y (bp) | G9: Spread 10Y (bp)
A10: =US_Yields!A4 | B10: =US_Yields!H4 | C10: =US_Yields!M4 | D10: =IFERROR(INDEX(JP_Yields!B$4:B$1000,MATCH($A10,JP_Yields!A$4:A$1000,0)),) | E10: =IFERROR(INDEX(JP_Yields!K$4:K$1000,MATCH($A10,JP_Yields!A$4:A$1000,0)),) | F10: =IF(OR(D10="",B10=""),"",(B10-D10)*100) | G10: =IF(OR(E10="",C10=""),"",(C10-E10)*100)
A11: =US_Yields!A5 | B11: =US_Yields!H5 | C11: =US_Yields!M5 | D11: =IFERROR(INDEX(JP_Yields!B$4:B$1000,MATCH($A11,JP_Yields!A$4:A$1000,0)),) | E11: =IFERROR(INDEX(JP_Yields!K$4:K$1000,MATCH($A11,JP_Yields!A$4:A$1000,0)),) | F11: =IF(OR(D11="",B11=""),"",(B11-D11)*100) | G11: =IF(OR(E11="",C11=""),"",(C11-E11)*100)
A12: =US_Yields!A6 | B12: =US_Yields!H6 | C12: =US_Yields!M6 | D12: =IFERROR(INDEX(JP_Yields!B$4:B$1000,MATCH($A12,JP_Yields!A$4:A$1000,0)),) | E12: =IFERROR(INDEX(JP_Yields!K$4:K$1000,MATCH($A12,JP_Yields!A$4:A$1000,0)),) | F12: =IF(OR(D12="",B12=""),"",(B12-D12)*100) | G12: =IF(OR(E12="",C12=""),"",(C12-E12)*100)
A13: =US_Yields!A7 | B13: =US_Yields!H7 | C13: =US_Yields!M7 | D13: =IFERROR(INDEX(JP_Yields!B$4:B$1000,MATCH($A13,JP_Yields!A$4:A$1000,0)),) | E13: =IFERROR(INDEX(JP_Yields!K$4:K$1000,MATCH($A13,JP_Yields!A$4:A$1000,0)),) | F13: =IF(OR(D13="",B13=""),"",(B13-D13)*100) | G13: =IF(OR(E13="",C13=""),"",(C13-E13)*100)
A14: =US_Yields!A8 | B14: =US_Yields!H8 | C14: =US_Yields!M8 | D14: =IFERROR(INDEX(JP_Yields!B$4:B$1000,MATCH($A14,JP_Yields!A$4:A$1000,0)),) | E14: =IFERROR(INDEX(JP_Yields!K$4:K$1000,MATCH($A14,JP_Yields!A$4:A$1000,0)),) | F14: =IF(OR(D14="",B14=""),"",(B14-D14)*100) | G14: =IF(OR(E14="",C14=""),"",(C14-E14)*100)
A15: =US_Yields!A9 | B15: =US_Yields!H9 | C15: =US_Yields!M9 | D15: =IFERROR(INDEX(JP_Yields!B$4:B$1000,MATCH($A15,JP_Yields!A$4:A$1000,0)),) | E15: =IFERROR(INDEX(JP_Yields!K$4:K$1000,MATCH($A15,JP_Yields!A$4:A$1000,0)),) | F15: =IF(OR(D15="",B15=""),"",(B15-D15)*100) | G15: =IF(OR(E15="",C15=""),"",(C15-E15)*100)
A16: =US_Yields!A10 | B16: =US_Yields!H10 | C16: =US_Yields!M10 | D16: =IFERROR(INDEX(JP_Yields!B$4:B$1000,MATCH($A16,JP_Yields!A$4:A$1000,0)),) | E16: =IFERROR(INDEX(JP_Yields!K$4:K$1000,MATCH($A16,JP_Yields!A$4:A$1000,0)),) | F16: =IF(OR(D16="",B16=""),"",(B16-D16)*100) | G16: =IF(OR(E16="",C16=""),"",(C16-E16)*100)
A17: =US_Yields!A11 | B17: =US_Yields!H11 | C17: =US_Yields!M11 | D17: =IFERROR(INDEX(JP_Yields!B$4:B$1000,MATCH($A17,JP_Yields!A$4:A$1000,0)),) | E17: =IFERROR(INDEX(JP_Yields!K$4:K$1000,MATCH($A17,JP_Yields!A$4:A$1000,0)),) | F17: =IF(OR(D17="",B17=""),"",(B17-D17)*100) | G17: =IF(OR(E17="",C17=""),"",(C17-E17)*100)
A18: =US_Yields!A12 | B18: =US_Yields!H12 | C18: =US_Yields!M12 | D18: =IFERROR(INDEX(JP_Yields!B$4:B$1000,MATCH($A18,JP_Yields!A$4:A$1000,0)),) | E18: =IFERROR(INDEX(JP_Yields!K$4:K$1000,MATCH($A18,JP_Yields!A$4:A$1000,0)),) | F18: =IF(OR(D18="",B18=""),"",(B18-D18)*100) | G18: =IF(OR(E18="",C18=""),"",(C18-E18)*100)
A19: =US_Yields!A13 | B19: =US_Yields!H13 | C19: =US_Yields!M13 | D19: =IFERROR(INDEX(JP_Yields!B$4:B$1000,MATCH($A19,JP_Yields!A$4:A$1000,0)),) | E19: =IFERROR(INDEX(JP_Yields!K$4:K$1000,MATCH($A19,JP_Yields!A$4:A$1000,0)),) | F19: =IF(OR(D19="",B19=""),"",(B19-D19)*100) | G19: =IF(OR(E19="",C19=""),"",(C19-E19)*100)
A20: =US_Yields!A14 | B20: =US_Yields!H14 | C20: =US_Yields!M14 | D20: =IFERROR(INDEX(JP_Yields!B$4:B$1000,MATCH($A20,JP_Yields!A$4:A$1000,0)),) | E20: =IFERROR(INDEX(JP_Yields!K$4:K$1000,MATCH($A20,JP_Yields!A$4:A$1000,0)),) | F20: =IF(OR(D20="",B20=""),"",(B20-D20)*100) | G20: =IF(OR(E20="",C20=""),"",(C20-E20)*100)
A21: =US_Yields!A15 | B21: =US_Yields!H15 | C21: =US_Yields!M15 | D21: =IFERROR(INDEX(JP_Yields!B$4:B$1000,MATCH($A21,JP_Yields!A$4:A$1000,0)),) | E21: =IFERROR(INDEX(JP_Yields!K$4:K$1000,MATCH($A21,JP_Yields!A$4:A$1000,0)),) | F21: =IF(OR(D21="",B21=""),"",(B21-D21)*100) | G21: =IF(OR(E21="",C21=""),"",(C21-E21)*100)
... A70: =US_Yields!A64 | B70: =US_Yields!H64 | C70: =US_Yields!M64 | D70: =IFERROR(INDEX(JP_Yields!B$4:B$1000,MATCH($A70,JP_Yields!A$4:A$1000,0)),) | E70: =IFERROR(INDEX(JP_Yields!K$4:K$1000,MATCH($A70,JP_Yields!A$4:A$1000,0)),) | F70: =IF(OR(D70="",B70=""),"",(B70-D70)*100) | G70: =IF(OR(E70="",C70=""),"",(C70-E70)*100)

Sheet Carry_PnL
A1: Q1 2026 USD/JPY 1-Year Forward Carry-Trade Analysis
A3: Inputs
A4: Quarter-start USD/JPY spot (anchor) | D4: =FX_USDJPY!B4
A5: Quarter-end USD/JPY spot | D5: =INDEX(FX_USDJPY!B4:B1000, COUNT(FX_USDJPY!B4:B1000))
A6: US 1Y yield at quarter start (%) | D6: =US_Yields!H4
A7: JP 1Y yield at quarter start (%) | D7: =JP_Yields!B4
A8: US 1Y yield at quarter end (%) | D8: =INDEX(US_Yields!H4:H1000, COUNT(US_Yields!H4:H1000))
A9: JP 1Y yield at quarter end (%) | D9: =INDEX(JP_Yields!B4:B1000, COUNT(JP_Yields!B4:B1000))
A10: Notional (USD) | D10: 1000000
A12: Computed
A13: CIP 1Y implied fwd (start, JPY/USD) | D13: =D4*(1+D6/100)/(1+D7/100)
A14: CIP 1Y implied fwd (end, JPY/USD) | D14: =D5*(1+D8/100)/(1+D9/100)
A15: Realized FX move (%) | D15: =D5/D4 - 1
A16: Nominal 1Y carry diff (US−JP, %) | D16: =D6 - D7
A17: Q1 MTM PnL on long-USD/JPY 1Y fwd (USD) | D17: =D10*((D5-D13)/D13)
A18: — spot component (USD) | D18: =D10*(D5-D4)/D4
A19: — carry component (USD) | D19: =D10*(D4-D13)/D13
A20: — residual (USD) | D20: =D17 - D18 - D19
A22: Real-rate overlay (WEO 2026 CPI projections)
A23: US CPI 2026 (%) | D23: =WEO_Macro!E9
A24: JP CPI 2026 (%) | D24: =WEO_Macro!E10
A25: US 1Y real (start, %) | D25: =D6 - D23
A26: JP 1Y real (start, %) | D26: =D7 - D24
A27: Real 1Y differential (US−JP, pp) | D27: =D25 - D26

Sheet Scenarios
A1: Scenario sensitivities — overrides applied to quarter-end inputs
A3: Scenario | B3: Spot end shock (×) | C3: US 1Y end shift (pp) | D3: JP 1Y end shift (pp) | E3: Spot end (JPY/USD) | F3: Implied fwd (JPY/USD) | G3: PnL (USD)
A4: Baseline | B4: 1 | C4: 0 | D4: 0 | E4: =Carry_PnL!$D$5*B4 | F4: =E4*(1+(Carry_PnL!$D$8+C4)/100)/(1+(Carry_PnL!$D$9+D4)/100) | G4: =Carry_PnL!$D$10*(F4-Carry_PnL!$D$13)/Carry_PnL!$D$13
A5: Fed −100bp + JPY +5% | B5: 0.95 | C5: -1 | D5: 0 | E5: =Carry_PnL!$D$5*B5 | F5: =E5*(1+(Carry_PnL!$D$8+C5)/100)/(1+(Carry_PnL!$D$9+D5)/100) | G5: =Carry_PnL!$D$10*(F5-Carry_PnL!$D$13)/Carry_PnL!$D$13
A6: BoJ +50bp + JPY −5% | B6: 1.05 | C6: 0 | D6: 0.5 | E6: =Carry_PnL!$D$5*B6 | F6: =E6*(1+(Carry_PnL!$D$8+C6)/100)/(1+(Carry_PnL!$D$9+D6)/100) | G6: =Carry_PnL!$D$10*(F6-Carry_PnL!$D$13)/Carry_PnL!$D$13
