Workbook

Sheet US_Yields
A1: Source: U.S. Department of the Treasury — Daily Treasury Par Yield Curve Rates
A3: Date | B3: 1 Mo | C3: 1.5 Month | D3: 2 Mo | E3: 3 Mo | F3: 4 Mo | G3: 6 Mo | H3: 1 Yr | I3: 2 Yr | J3: 3 Yr | K3: 5 Yr | L3: 7 Yr | M3: 10 Yr | N3: 20 Yr | O3: 30 Yr
A4: 46024
A5: 46027
A6: 46028
A7: 46029
A8: 46030
A9: 46031
A10: 46034
A11: 46035
A12: 46036
A13: 46037
A14: 46038
A15: 46042
... A64: 46112

Sheet JP_Yields
A1: Source: Ministry of Finance Japan — JGB Constant Maturity (jgbcme)
A3: Date | B3: 1Y | C3: 2Y | D3: 3Y | E3: 4Y | F3: 5Y | G3: 6Y | H3: 7Y | I3: 8Y | J3: 9Y | K3: 10Y | L3: 15Y | M3: 20Y | N3: 25Y | O3: 30Y | P3: 40Y
A4: 46027
A5: 46028
A6: 46029
A7: 46030
A8: 46031
A9: 46035
A10: 46036
A11: 46037
A12: 46038
A13: 46041
A14: 46042
A15: 46043
... A61: 46112

Sheet FX_USDJPY
A1: Source: FRED DEXJPUS — Japanese Yen to U.S. Dollar spot rate
A3: Date | B3: USD/JPY
A4: 46022
A5: 46024
A6: 46027
A7: 46028
A8: 46029
A9: 46030
A10: 46031
A11: 46034
A12: 46035
A13: 46036
A14: 46037
A15: 46038
... A65: 46112

Sheet WEO_Macro
A1: Source: IMF World Economic Outlook (DataMapper API)
A3: Indicator | B3: Country | C3: 2024 | D3: 2025 | E3: 2026 | F3: 2027 | G3: 2028 | H3: 2029 | I3: 2030 | J3: 2031
A4: Real GDP growth (%) | B4: NGDP_RPCH
B5: USA
B6: JPN
A8: Inflation, avg CPI (%) | B8: PCPIPCH
B9: USA
B10: JPN
A12: Gen govt gross debt (% GDP) | B12: GGXWDG_NGDP
B13: USA
B14: JPN
A16: Current account balance (% GDP) | B16: BCA_NGDPD
B17: USA
B18: JPN

Sheet Spreads
A1: Daily US − JP yield differential (basis points). Lookup JP by date.
A3: Tenor | B3: Mean (bp) | C3: Stdev (bp) | D3: Q1 close (bp)
A4: 1Y
A5: 10Y
A9: Date | B9: US 1Y (%) | C9: US 10Y (%) | D9: JP 1Y (%) | E9: JP 10Y (%) | F9: Spread 1Y (bp) | G9: Spread 10Y (bp)
A10: =US_Yields!A4
A11: =US_Yields!A5
A12: =US_Yields!A6
A13: =US_Yields!A7
A14: =US_Yields!A8
A15: =US_Yields!A9
A16: =US_Yields!A10
A17: =US_Yields!A11
A18: =US_Yields!A12
A19: =US_Yields!A13
A20: =US_Yields!A14
A21: =US_Yields!A15
... A70: =US_Yields!A64

Sheet Carry_PnL
A1: Q1 2026 USD/JPY 1-Year Forward Carry-Trade Analysis
A3: Inputs
A4: Quarter-start USD/JPY spot (anchor)
A5: Quarter-end USD/JPY spot
A6: US 1Y yield at quarter start (%)
A7: JP 1Y yield at quarter start (%)
A8: US 1Y yield at quarter end (%)
A9: JP 1Y yield at quarter end (%)
A10: Notional (USD)
A12: Computed
A13: CIP 1Y implied fwd (start, JPY/USD)
A14: CIP 1Y implied fwd (end, JPY/USD)
... A27: Real 1Y differential (US−JP, pp)

Sheet Scenarios
A1: Scenario sensitivities — overrides applied to quarter-end inputs
A3: Scenario | B3: Spot end shock (×) | C3: US 1Y end shift (pp) | D3: JP 1Y end shift (pp) | E3: Spot end (JPY/USD) | F3: Implied fwd (JPY/USD) | G3: PnL (USD)
A4: Baseline | B4: 1 | C4: 0 | D4: 0
A5: Fed −100bp + JPY +5% | B5: 0.95 | C5: -1 | D5: 0
A6: BoJ +50bp + JPY −5% | B6: 1.05 | C6: 0 | D6: 0.5
